{
  "tests": [
    {
      "name": "Dynamic Lists Test",
      "setup": "",
      "run": "./gradlew manipulatingarrays-dynamiclists-test",
      "input": "",
      "output": "",
      "comparison": "included",
      "timeout": 10,
      "points": null
    },
    {
      "name": "Modifying Arrays Test",
      "setup": "",
      "run": "./gradlew arrays-modifyingarrays-test",
      "input": "",
      "output": "",
      "comparison": "included",
      "timeout": 10,
      "points": null
    },
    {
      "name": "Dynamic Arrays Test",
      "setup": "",
      "run": "./gradlew arraylists-dynamicarrays-test",
      "input": "",
      "output": "",
      "comparison": "included",
      "timeout": 10,
      "points": null
    },
    {
      "name": "Dynamic Strings Test",
      "setup": "",
      "run": "./gradlew strings-dynamicstrings-test",
      "input": "",
      "output": "",
      "comparison": "included",
      "timeout": 10,
      "points": null
    }
  ]
}